procstar/__init__.py
procstar/proto.py
procstar/spec.py
procstar/agent/__init__.py
procstar/agent/__main__.py
procstar/agent/conn.py
procstar/agent/exc.py
procstar/agent/proc.py
procstar/agent/server.py
procstar/http/__init__.py
procstar/http/client.py
procstar/lib/__init__.py
procstar/lib/asyn.py
procstar/lib/json.py
procstar/lib/logging.py
procstar/lib/net.py
procstar/lib/py.py
procstar/lib/string.py
procstar/lib/time.py
procstar/testing/__init__.py
procstar/testing/agent.py
procstar/testing/inst.py
procstar/testing/localhost.crt
procstar/testing/localhost.key
procstar/testing/proc.py
procstar-1.1.0.dist-info/licenses/LICENSE
procstar-1.1.0.dist-info/METADATA
procstar-1.1.0.dist-info/WHEEL
procstar-1.1.0.dist-info/top_level.txt
procstar-1.1.0.dist-info/RECORD
