Metadata-Version: 2.4
Name: procstar
Version: 1.1.0
Summary: Run my stuff!
Author-email: Alex Samuel <alex@alexsamuel.net>
License: BSD-3-Clause
Project-URL: Repository, https://github.com/apsis-scheduler/procstar
Classifier: License :: OSI Approved :: MIT License
Classifier: Programming Language :: Python :: 3
Requires-Python: >=3.13
License-File: LICENSE
Requires-Dist: orjson>=3
Requires-Dist: msgpack>=1
Requires-Dist: requests
Requires-Dist: websockets>=15
Provides-Extra: dev
Requires-Dist: build; extra == "dev"
Requires-Dist: httpx; extra == "dev"
Requires-Dist: pytest; extra == "dev"
Requires-Dist: pytest-asyncio; extra == "dev"
Requires-Dist: bump-my-version; extra == "dev"
Requires-Dist: sphinx; extra == "dev"
Requires-Dist: sphinx-rtd-theme; extra == "dev"
Dynamic: license-file
